lightcsv.py
lightcsv-0.2.3.dist-info/LICENSE
lightcsv-0.2.3.dist-info/WHEEL
lightcsv-0.2.3.dist-info/METADATA
lightcsv-0.2.3.dist-info/RECORD
