Metadata-Version: 2.1
Name: lightcsv
Version: 0.2.3
Summary: Simple pure Python CSV parser
Home-page: https://github.com/boriel/lightcsv
License: MIT
Keywords: csv,CSV
Author: Jose Rodriguez
Author-email: boriel@gmail.com
Requires-Python: >=3.8,<4.0
Classifier: License :: OSI Approved :: MIT License
Classifier: Programming Language :: Python :: 3
Classifier: Programming Language :: Python :: 3.10
Classifier: Programming Language :: Python :: 3.8
Classifier: Programming Language :: Python :: 3.9
Project-URL: Repository, https://github.com/boriel/lightcsv
